asyncpg_queue/__init__.py
asyncpg_queue/bootstrap.py
asyncpg_queue/py.typed
asyncpg_queue/queue.py
asyncpg_queue/version/20230111.sql
asyncpg_queue/worker.py
asyncpg_queue-0.1.0.dist-info/LICENSE
asyncpg_queue-0.1.0.dist-info/METADATA
asyncpg_queue-0.1.0.dist-info/WHEEL
asyncpg_queue-0.1.0.dist-info/RECORD
