Metadata-Version: 2.1
Name: asyncpg-queue
Version: 0.1.0
Summary: 
License: MIT
Author: nate giraldi
Author-email: ng269@cornell.edu
Requires-Python: >=3.11,<3.12
Classifier: Development Status :: 4 - Beta
Classifier: Intended Audience :: Developers
Classifier: License :: OSI Approved :: MIT License
Classifier: Natural Language :: English
Classifier: Operating System :: OS Independent
Classifier: Programming Language :: Python :: 3
Classifier: Programming Language :: Python :: 3.11
Classifier: Programming Language :: Python :: 3 :: Only
Classifier: Programming Language :: Python :: 3.11
Requires-Dist: asyncpg (>=0.26,<0.28)
